Products.SiteErrorLog-6.0-py3.11-nspkg.pth
Products/SiteErrorLog/SiteErrorLog.py
Products/SiteErrorLog/__init__.py
Products/SiteErrorLog/configure.zcml
Products/SiteErrorLog/interfaces.py
Products/SiteErrorLog/tests/__init__.py
Products/SiteErrorLog/tests/testInitialization.py
Products/SiteErrorLog/tests/testSiteErrorLog.py
Products/SiteErrorLog/www/main.pt
Products/SiteErrorLog/www/showEntry.pt
Products.SiteErrorLog-6.0.dist-info/LICENSE.txt
Products.SiteErrorLog-6.0.dist-info/METADATA
Products.SiteErrorLog-6.0.dist-info/WHEEL
Products.SiteErrorLog-6.0.dist-info/namespace_packages.txt
Products.SiteErrorLog-6.0.dist-info/top_level.txt
Products.SiteErrorLog-6.0.dist-info/RECORD
