Metadata-Version: 2.1
Name: Products.SiteErrorLog
Version: 6.0
Summary: Error log for Zope.
Home-page: https://github.com/zopefoundation/Products.SiteErrorLog
Author: Zope Foundation and Contributors
Author-email: zope-dev@zope.dev
License: ZPL 2.1
Project-URL: Issue Tracker, https://github.com/zopefoundation/Products.SiteErrorLog/issues
Project-URL: Sources, https://github.com/zopefoundation/Products.SiteErrorLog
Classifier: Development Status :: 5 - Production/Stable
Classifier: Intended Audience :: Developers
Classifier: License :: OSI Approved :: Zope Public License
Classifier: Framework :: Zope
Classifier: Framework :: Zope :: 5
Classifier: Operating System :: OS Independent
Classifier: Programming Language :: Python
Classifier: Programming Language :: Python :: 3
Classifier: Programming Language :: Python :: 3.7
Classifier: Programming Language :: Python :: 3.8
Classifier: Programming Language :: Python :: 3.9
Classifier: Programming Language :: Python :: 3.10
Classifier: Programming Language :: Python :: 3.11
Classifier: Programming Language :: Python :: Implementation
Classifier: Programming Language :: Python :: Implementation :: CPython
Requires-Python: >=3.7
License-File: LICENSE.txt
Requires-Dist: setuptools
Requires-Dist: AccessControl
Requires-Dist: Acquisition
Requires-Dist: transaction
Requires-Dist: zExceptions
Requires-Dist: Zope (>=4.0b9.dev0)
Requires-Dist: zope.component
Requires-Dist: zope.interface
Requires-Dist: zope.event
